embermaker/__init__.py
embermaker/defaults/colors.xlsx
embermaker/defaults/convert.py
embermaker/defaults/paramdefs.md
embermaker/defaults/riskdefs_en.json
embermaker/defaults/riskdefs_es.json
embermaker/defaults/riskdefs_fr.json
embermaker/defaults/riskdefs_nl.json
embermaker/drawinglib/__init__.py
embermaker/drawinglib/canvas.py
embermaker/drawinglib/canvas_base.py
embermaker/drawinglib/canvas_pdf.py
embermaker/drawinglib/canvas_svg.py
embermaker/drawinglib/helpers.py
embermaker/ember.py
embermaker/ember_utils.py
embermaker/embergraph.py
embermaker/graphbase.py
embermaker/helpers.py
embermaker/legend.py
embermaker/lineplot.py
embermaker/parameters.py
embermaker/readembers.py
embermaker-2.2.dist-info/LICENCE.md
embermaker-2.2.dist-info/METADATA
embermaker-2.2.dist-info/WHEEL
embermaker-2.2.dist-info/RECORD
