Metadata-Version: 2.3
Name: embermaker
Version: 2.2
Summary: Software library to (re)produce burning ember and related diagrams of the style used in IPCC reports
License: GPL-3.0-or-later
Keywords: climate change,impacts,IPCC,burning embers
Author: Philippe Marbaix
Author-email: philippe.marbaix@uclouvain.be>
Maintainer: Philippe Marbaix
Maintainer-email: philippe.marbaix@uclouvain.be>
Requires-Python: <4,>=3.10
Classifier: License :: OSI Approved :: GNU General Public License v3 or later (GPLv3+)
Classifier: Programming Language :: Python :: 3
Classifier: Programming Language :: Python :: 3.10
Classifier: Programming Language :: Python :: 3.11
Classifier: Programming Language :: Python :: 3.12
Classifier: Programming Language :: Python :: 3.13
Requires-Dist: defusedxml (>=0.7)
Requires-Dist: lxml (>=5.2)
Requires-Dist: markdown (>=3.8)
Requires-Dist: numpy (>=2.2.6)
Requires-Dist: openpyxl (>=3.1)
Requires-Dist: pdf2image (>=1.17)
Requires-Dist: reportlab (>=4.4)
Requires-Dist: svg.py (>=1.6)
